proximitypyhash
