Metadata-Version: 1.2
Name: proximitypyhash
Version: 0.2.1
Summary: Pygeohash for proximity queries
Home-page: https://github.com/dice89/proximityhash
Author: Ashwin Nair/Alexander Mueller
Author-email: alexander.mueller@gmail.com
License: MIT
Download-URL: https://github.com/dice89/proximityhash/archive/0.2.1.tar.gz
Keywords: geohash,optimizer,compression,geo,latitude,longitude,coordinates,proximity,circle
Platform: UNKNOWN
Classifier: Development Status :: 5 - Production/Stable
Classifier: Environment :: Console
Classifier: Intended Audience :: Developers
Classifier: License :: OSI Approved :: Apache Software License
Classifier: Programming Language :: Python
Classifier: Topic :: Software Development :: Libraries :: Python Modules
Classifier: Topic :: Utilities
Classifier: Programming Language :: Python :: 2
Classifier: Programming Language :: Python :: 2.6
Classifier: Programming Language :: Python :: 2.7
Classifier: Programming Language :: Python :: 3
Classifier: Programming Language :: Python :: 3.3
Classifier: Programming Language :: Python :: 3.4
Classifier: Programming Language :: Python :: 3.5
Classifier: Programming Language :: Python :: 3.6
Requires-Python: >=2.6, !=3.0.*, !=3.1.*, !=3.2.*, <4
